{
  "tutorials": [
    {
      "title": "Title 12 adas d ",
      "description": "Qwerty description 12a asdf",
      "published": 1,
      "id": 1
    },
    {
      "id": 2,
      "title": "Title 2",
      "description": "Qwerty description 2",
      "published": true
    },
    {
      "title": "Title 3",
      "description": "Qwerty description 3",
      "published": 0,
      "id": 3
    },
    {
      "id": 4,
      "title": "Title 4",
      "description": "Qwerty description 4",
      "published": false
    },
    {
      "title": "Title 5",
      "description": "Qwerty description 5",
      "published": 0,
      "id": 5
    },
    {
      "id": 6,
      "title": "ABC",
      "description": "Description ABC",
      "published": true
    }
  ]
}